yase/__init__.py
yase/encoders.py
yase/evaluation.py
yase/mergingmethods.py
yase/utils.py
yase/arrow/__init__.py
yase/arrow/embedding.py
yase/arrow/stringprocessing.py
yase/pandas/__init__.py
yase/pandas/embedding.py
yase/pandas/stringprocessing.py
YASE-1.0.1.dist-info/METADATA
YASE-1.0.1.dist-info/WHEEL
YASE-1.0.1.dist-info/top_level.txt
YASE-1.0.1.dist-info/RECORD
