Metadata-Version: 2.1
Name: YASE
Version: 1.0.1
Home-page: https://github.com/VHRanger/YASE/
Author: Matt Ranger
License: MIT
Requires-Dist: gensim
Requires-Dist: numpy
Requires-Dist: pandas
Requires-Dist: scikit-learn
Requires-Dist: pytest
Requires-Dist: pytest-cov
